askdata/__init__.py
askdata/askdata_client.py
askdata/askdata_pandas_extension.py
askdata/catalog.py
askdata/channel.py
askdata/dataset.py
askdata/human2query.py
askdata/insight.py
askdata/insight_definition.py
askdata/integration.py
askdata/security.py
askdata/smartgraph.py
askdata/smartquery.py
askdata/test.py
askdata/askdata_config/base_url.yaml
askdata/askdata_config/compression_tokens.json
askdata/drivers/alphavantage.py
askdata/drivers/dataset.py
askdata/integrations/aircall_api.py
askdata/integrations/alphavantage.py
askdata/integrations/facebook_api.py
askdata/integrations/google_analytics.py
askdata/integrations/google_api.py
askdata/integrations/hubspot_api.py
askdata/integrations/salesforce_contacts.py
askdata/integrations/tableau_server.py
askdata/integrations/wikipedia_table.py
askdata-1.4.53.dist-info/LICENSE
askdata-1.4.53.dist-info/METADATA
askdata-1.4.53.dist-info/WHEEL
askdata-1.4.53.dist-info/top_level.txt
askdata-1.4.53.dist-info/RECORD
