Metadata-Version: 2.1
Name: askdata
Version: 1.4.53
Summary: The official Askdata Python SDK
Home-page: https://github.com/AskdataInc/askdata-api-python-client
Author: ['Giuseppe De Maio', 'Matteo Giacalone', 'Luca Sarcona', 'Simone Di Somma', 'Massimiliano Bruni', 'Oscar Caruso', 'Gennaro Vaccaro', 'Maria Luisa Croci', 'Enrico Sammarco']
Author-email: datascience@askdata.com
License: Apache License 2.0
Keywords: nlp
Classifier: Programming Language :: Python :: 3
Classifier: Operating System :: OS Independent
Classifier: License :: OSI Approved :: MIT License
Classifier: Development Status :: 3 - Alpha
Requires-Python: >=3, <4
License-File: LICENSE
Requires-Dist: pandas (>=1.1.2)
Requires-Dist: numpy (>=1.19.2)
Requires-Dist: pyarrow (==7.0.0)
Requires-Dist: PyYAML (>=5.1)
Requires-Dist: yaml-1.3
Requires-Dist: requests (>=2)
Requires-Dist: urllib3 (>=1)
Requires-Dist: sqlalchemy (>=1.3.8)
Requires-Dist: mysql-connector (>=2.2.9)
Requires-Dist: NotebookScripter (==6.0.0)
Requires-Dist: jsons
Requires-Dist: google-ads
Requires-Dist: google-api-python-client (>=2.42.0)
Requires-Dist: oauthlib (>=3.2.0)
Requires-Dist: oauth2client (==4.1.3)
Requires-Dist: facebook-business (>=12.0.1)
Requires-Dist: hubspot3 (>=3.2.51)
